ven.py
ven-0.4.1.dist-info/DESCRIPTION.rst
ven-0.4.1.dist-info/entry_points.txt
ven-0.4.1.dist-info/METADATA
ven-0.4.1.dist-info/metadata.json
ven-0.4.1.dist-info/RECORD
ven-0.4.1.dist-info/top_level.txt
ven-0.4.1.dist-info/WHEEL
